allib/__init__.py
allib/__main__.py
allib/app.py
allib/py.typed
allib/activelearning/__init__.py
allib/activelearning/ats.py
allib/activelearning/autostop.py
allib/activelearning/autostoplarge.py
allib/activelearning/autotar.py
allib/activelearning/autotarensemble.py
allib/activelearning/base.py
allib/activelearning/catalog.py
allib/activelearning/cmh.py
allib/activelearning/ensembles.py
allib/activelearning/estimator.py
allib/activelearning/factory.py
allib/activelearning/fixed.py
allib/activelearning/helperfunctions.py
allib/activelearning/insclass.py
allib/activelearning/labelmethods.py
allib/activelearning/learnersequence.py
allib/activelearning/ml_based.py
allib/activelearning/mostcertain.py
allib/activelearning/oracles.py
allib/activelearning/poolbased.py
allib/activelearning/prob_ensembles.py
allib/activelearning/qbc.py
allib/activelearning/random.py
allib/activelearning/selectioncriterion.py
allib/activelearning/sequence.py
allib/activelearning/synthetictrain.py
allib/activelearning/target.py
allib/activelearning/tsvm.py
allib/activelearning/uncertainty.py
allib/analysis/__init__.py
allib/analysis/analysis.py
allib/analysis/base.py
allib/analysis/classificationplotter.py
allib/analysis/experiments.py
allib/analysis/initialization.py
allib/analysis/plotter.py
allib/analysis/simulation.py
allib/analysis/statistics.py
allib/analysis/summarize.py
allib/analysis/tablecollector.py
allib/analysis/tarplotter.py
allib/balancing/__init__.py
allib/balancing/base.py
allib/balancing/catalog.py
allib/balancing/double.py
allib/balancing/factory.py
allib/balancing/randomoversampling.py
allib/balancing/triple.py
allib/balancing/undersample.py
allib/benchmarking/__init__.py
allib/benchmarking/datasets.py
allib/benchmarking/jobs.py
allib/benchmarking/reviews.py
allib/configurations/__init__.py
allib/configurations/base.py
allib/configurations/catalog.py
allib/configurations/ensemble.py
allib/configurations/tarbaselines.py
allib/environment/__init__.py
python_allib-0.5.3.dist-info/LICENSE
python_allib-0.5.3.dist-info/METADATA
python_allib-0.5.3.dist-info/WHEEL
python_allib-0.5.3.dist-info/top_level.txt
python_allib-0.5.3.dist-info/RECORD
